toolbox/__init__.py
toolbox/__main__.py
toolbox/commands.py
toolbox/errors.py
toolbox/members.py
toolbox/messages.py
toolbox/py.typed
toolbox/roles.py
toolbox/strings.py
hikari_toolbox-0.1.7.dist-info/LICENSE
hikari_toolbox-0.1.7.dist-info/METADATA
hikari_toolbox-0.1.7.dist-info/WHEEL
hikari_toolbox-0.1.7.dist-info/top_level.txt
hikari_toolbox-0.1.7.dist-info/RECORD
